crsmongo/__init__.py
crsmongo/crsmongo.py
crsmongo-1.0.6.dist-info/LICENSE
crsmongo-1.0.6.dist-info/METADATA
crsmongo-1.0.6.dist-info/WHEEL
crsmongo-1.0.6.dist-info/top_level.txt
crsmongo-1.0.6.dist-info/RECORD
